betterdisco_py-2025.6.11.dist-info/licenses/LICENSE
disco/__init__.py
disco/cli.py
disco/client.py
disco/state.py
disco/api/__init__.py
disco/api/client.py
disco/api/http.py
disco/api/ratelimit.py
disco/bot/__init__.py
disco/bot/bot.py
disco/bot/command.py
disco/bot/parser.py
disco/bot/plugin.py
disco/bot/storage.py
disco/gateway/__init__.py
disco/gateway/client.py
disco/gateway/events.py
disco/gateway/ipc.py
disco/gateway/packets.py
disco/gateway/sharder.py
disco/gateway/encoding/__init__.py
disco/gateway/encoding/base.py
disco/gateway/encoding/etf.py
disco/gateway/encoding/json.py
disco/types/__init__.py
disco/types/application.py
disco/types/base.py
disco/types/channel.py
disco/types/guild.py
disco/types/integration.py
disco/types/invite.py
disco/types/message.py
disco/types/oauth.py
disco/types/permissions.py
disco/types/reactions.py
disco/types/user.py
disco/types/voice.py
disco/types/webhook.py
disco/util/__init__.py
disco/util/backdoor.py
disco/util/chains.py
disco/util/config.py
disco/util/crypto.py
disco/util/emitter.py
disco/util/enum.py
disco/util/functional.py
disco/util/hashmap.py
disco/util/limiter.py
disco/util/logging.py
disco/util/metaclass.py
disco/util/paginator.py
disco/util/sanitize.py
disco/util/serializer.py
disco/util/snowflake.py
disco/util/string.py
disco/util/threadlocal.py
disco/util/websocket.py
disco/voice/__init__.py
disco/voice/client.py
disco/voice/opus.py
disco/voice/packets.py
disco/voice/playable.py
disco/voice/player.py
disco/voice/queue.py
disco/voice/udp.py
betterdisco_py-2025.6.11.dist-info/METADATA
betterdisco_py-2025.6.11.dist-info/WHEEL
betterdisco_py-2025.6.11.dist-info/top_level.txt
betterdisco_py-2025.6.11.dist-info/RECORD
