Metadata-Version: 2.4
Name: betterdisco-py
Version: 2025.6.11
Summary: A Discord API library, written in Python, for those that like to dance. [QUEUE COWBOY BEBOP THEME]
Author: Andrei Zbikowski
Maintainer: The BetterDisco Team
License: MIT License
Project-URL: Repository, https://github.com/elderlabs/BetterDisco.git
Keywords: discord,disco,disco-py,bdisco,betterdisco,betterdisco-py
Classifier: Development Status :: 4 - Beta
Classifier: License :: OSI Approved :: MIT License
Classifier: Intended Audience :: Developers
Classifier: Natural Language :: English
Classifier: Operating System :: OS Independent
Classifier: Programming Language :: Python :: 3
Classifier: Programming Language :: Python :: 3.9
Classifier: Programming Language :: Python :: 3.10
Classifier: Programming Language :: Python :: 3.11
Classifier: Programming Language :: Python :: 3.12
Classifier: Topic :: Internet
Classifier: Topic :: Software Development :: Libraries
Classifier: Topic :: Software Development :: Libraries :: Python Modules
Classifier: Topic :: Utilities
Requires-Python: >=3.9
License-File: LICENSE
Requires-Dist: gevent==25.5.1
Requires-Dist: requests==2.32.4
Requires-Dist: websocket-client==1.8.0
Provides-Extra: all
Requires-Dist: betterdisco-py[http,performance,sharding,voice,yaml]; extra == "all"
Provides-Extra: http
Requires-Dist: flask>=3.0.3; extra == "http"
Provides-Extra: performance
Requires-Dist: erlpack>=1.0.0; extra == "performance"
Requires-Dist: isal>=1.7.0; extra == "performance"
Requires-Dist: regex>=2024.7.24; extra == "performance"
Requires-Dist: pylibyaml>=0.1.0; extra == "performance"
Requires-Dist: ujson>=5.10.0; extra == "performance"
Requires-Dist: wsaccel>=0.6.6; extra == "performance"
Provides-Extra: redis
Requires-Dist: redis>=5.0.8; extra == "redis"
Requires-Dist: hiredis>=3.0.0; extra == "redis"
Provides-Extra: sharding
Requires-Dist: gipc>=1.6.0; extra == "sharding"
Requires-Dist: dill>=0.3.8; extra == "sharding"
Provides-Extra: voice
Requires-Dist: libnacl>=2.1.0; extra == "voice"
Provides-Extra: yaml
Requires-Dist: pyyaml>=6.0.2; extra == "yaml"
Dynamic: license-file
